mouse_joystick_interface/__about__.py
mouse_joystick_interface/__init__.py
mouse_joystick_interface/mouse_joystick_interface.py
mouse_joystick_interface-5.0.1.dist-info/AUTHORS
mouse_joystick_interface-5.0.1.dist-info/LICENSE
mouse_joystick_interface-5.0.1.dist-info/METADATA
mouse_joystick_interface-5.0.1.dist-info/WHEEL
mouse_joystick_interface-5.0.1.dist-info/top_level.txt
mouse_joystick_interface-5.0.1.dist-info/RECORD
