Metadata-Version: 2.1
Name: mouse-joystick-interface
Version: 5.0.1
Summary: Python interface to the Dudman lab Mouse Joystick Rig.
Author-email: Peter Polidoro <peter@polidoro.io>
Maintainer-email: Peter Polidoro <peter@polidoro.io>
License: Janelia Open-Source Software (3-clause BSD License)
Project-URL: Homepage, https://github.com/janelia-pypi/mouse_joystick_interface_python
Project-URL: Documentation, https://github.com/janelia-pypi/mouse_joystick_interface_python
Project-URL: Bug Tracker, https://github.com/janelia-pypi/mouse_joystick_interface_python/issues
Classifier: Development Status :: 4 - Beta
Classifier: License :: OSI Approved :: BSD License
Classifier: Programming Language :: Python :: 3 :: Only
Classifier: Topic :: Scientific/Engineering
Requires-Python: >=3.8
License-File: LICENSE
License-File: AUTHORS
Requires-Dist: modular-client
Requires-Dist: flatten-json
